sloweler.py
sloweler-1.0.0.dist-info/WHEEL
sloweler-1.0.0.dist-info/METADATA
sloweler-1.0.0.dist-info/RECORD
