Metadata-Version: 2.1
Name: sloweler
Version: 1.0.0
Summary: Slow text printing operation.
License: GNU-V3
Author: OwoNicoo
Author-email: 86409467+DiscordBotML@users.noreply.github.com
Requires-Python: >=3.9.6,<4.0.0
Classifier: License :: Other/Proprietary License
Classifier: Programming Language :: Python :: 3
Classifier: Programming Language :: Python :: 3.10
